Metadata-Version: 2.1
Name: matrix-operations-raja
Version: 0.0.1
Summary: it has a wide operation of matrix
Author-email: rajagopal <mugundhanrajagopal005@gmail.com>
Classifier: Programming Language :: Python :: 3
Classifier: License :: OSI Approved :: MIT License
Classifier: Operating System :: OS Independent
Requires-Python: >=3.7
License-File: LICENSE.txt
